richenum/__init__.py
richenum/enums.py
richenum-2.0.2.dist-info/AUTHORS.rst
richenum-2.0.2.dist-info/LICENSE.txt
richenum-2.0.2.dist-info/METADATA
richenum-2.0.2.dist-info/WHEEL
richenum-2.0.2.dist-info/top_level.txt
richenum-2.0.2.dist-info/RECORD
