Metadata-Version: 2.1
Name: richenum
Version: 2.0.2
Summary: Enum library for python.
Home-page: https://github.com/hearsaycorp/richenum
Author: Hearsay Social
Author-email: opensource@hearsaysocial.com
License: MIT
Keywords: python enum richenum
Platform: UNKNOWN
Classifier: Development Status :: 5 - Production/Stable
Classifier: License :: OSI Approved :: MIT License
Classifier: Programming Language :: Python
Classifier: Programming Language :: Python :: 3
Classifier: Programming Language :: Python :: 3.8
Classifier: Programming Language :: Python :: 3.9
Classifier: Programming Language :: Python :: 3.10
Classifier: Programming Language :: Python :: Implementation :: CPython
Classifier: Topic :: Software Development :: Libraries :: Python Modules
